m1key/COMMANDS.md
m1key/__init__.py
m1key/__main__.py
m1key/allCommands.py
m1key/education.py
m1key/haarcascade_frontalface_alt.xml
m1key/home.py
m1key/oneml.py
m1key/profile.jpeg
m1key/profile.py
m1key/profile.txt
m1key/resume.py
m1key/segment.py
m1key/skills.py
m1key/thug.py
m1key/tree.py
m1key/website.py
m1key-0.3.3.dist-info/LICENSE.txt
m1key-0.3.3.dist-info/METADATA
m1key-0.3.3.dist-info/WHEEL
m1key-0.3.3.dist-info/entry_points.txt
m1key-0.3.3.dist-info/top_level.txt
m1key-0.3.3.dist-info/RECORD
