Metadata-Version: 2.1
Name: m1key
Version: 0.3.3
Summary: A resume based package
Home-page: UNKNOWN
Author: Mithilesh Tiwari
Author-email: shubhamtiwari.tiwari84@gmail.com
License: MIT
Keywords: m1key
Platform: UNKNOWN
Classifier: Development Status :: 5 - Production/Stable
Classifier: Intended Audience :: Education
Classifier: License :: OSI Approved :: MIT License
Classifier: Programming Language :: Python :: 3
Classifier: Programming Language :: Python :: 3.7
Classifier: Programming Language :: Python :: 3.6
Requires-Dist: opencv-python
Requires-Dist: requests
Requires-Dist: matplotlib
Requires-Dist: numpy
Requires-Dist: scikit-learn
Requires-Dist: Pillow
Requires-Dist: anytree
